.gitignore
.travis.yml
LICENSE.txt
MANIFEST.in
README.md
setup.py
eigency/__init__.py
eigency/conversions.cpp
eigency/conversions.pxd
eigency/conversions.pyx
eigency/conversions_api.h
eigency/core.cpp
eigency/core.pxd
eigency/core.pyx
eigency/eigency_cpp.h
eigency/eigen_3.2.8/COPYING.BSD
eigency/eigen_3.2.8/COPYING.GPL
eigency/eigen_3.2.8/COPYING.LGPL
eigency/eigen_3.2.8/COPYING.MINPACK
eigency/eigen_3.2.8/COPYING.MPL2
eigency/eigen_3.2.8/COPYING.README
eigency/eigen_3.2.8/Eigen/Array
eigency/eigen_3.2.8/Eigen/Cholesky
eigency/eigen_3.2.8/Eigen/CholmodSupport
eigency/eigen_3.2.8/Eigen/Core
eigency/eigen_3.2.8/Eigen/Dense
eigency/eigen_3.2.8/Eigen/Eigen
eigency/eigen_3.2.8/Eigen/Eigen2Support
eigency/eigen_3.2.8/Eigen/Eigenvalues
eigency/eigen_3.2.8/Eigen/Geometry
eigency/eigen_3.2.8/Eigen/Householder
eigency/eigen_3.2.8/Eigen/IterativeLinearSolvers
eigency/eigen_3.2.8/Eigen/Jacobi
eigency/eigen_3.2.8/Eigen/LU
eigency/eigen_3.2.8/Eigen/LeastSquares
eigency/eigen_3.2.8/Eigen/MetisSupport
eigency/eigen_3.2.8/Eigen/OrderingMethods
eigency/eigen_3.2.8/Eigen/PaStiXSupport
eigency/eigen_3.2.8/Eigen/PardisoSupport
eigency/eigen_3.2.8/Eigen/QR
eigency/eigen_3.2.8/Eigen/QtAlignedMalloc
eigency/eigen_3.2.8/Eigen/SPQRSupport
eigency/eigen_3.2.8/Eigen/SVD
eigency/eigen_3.2.8/Eigen/Sparse
eigency/eigen_3.2.8/Eigen/SparseCholesky
eigency/eigen_3.2.8/Eigen/SparseCore
eigency/eigen_3.2.8/Eigen/SparseLU
eigency/eigen_3.2.8/Eigen/SparseQR
eigency/eigen_3.2.8/Eigen/StdDeque
eigency/eigen_3.2.8/Eigen/StdList
eigency/eigen_3.2.8/Eigen/StdVector
eigency/eigen_3.2.8/Eigen/SuperLUSupport
eigency/eigen_3.2.8/Eigen/UmfPackSupport
eigency/eigen_3.2.8/Eigen/src/Cholesky/LDLT.h
eigency/eigen_3.2.8/Eigen/src/Cholesky/LLT.h
eigency/eigen_3.2.8/Eigen/src/Cholesky/LLT_MKL.h
eigency/eigen_3.2.8/Eigen/src/CholmodSupport/CholmodSupport.h
eigency/eigen_3.2.8/Eigen/src/Core/Array.h
eigency/eigen_3.2.8/Eigen/src/Core/ArrayBase.h
eigency/eigen_3.2.8/Eigen/src/Core/ArrayWrapper.h
rmjarvis.eigency.egg-info/PKG-INFO
rmjarvis.eigency.egg-info/SOURCES.txt
rmjarvis.eigency.egg-info/dependency_links.txt
rmjarvis.eigency.egg-info/requires.txt
rmjarvis.eigency.egg-info/top_level.txt
