Metadata-Version: 1.1
Name: rmjarvis.eigency
Version: 1.77.1
Summary: Cython interface between the numpy arrays and the Matrix/Array classes of the Eigen C++ library
Home-page: https://github.com/wouterboomsma/eigency
Author: Wouter Boomsma
Author-email: wb@di.ku.dk
License: MIT
Platform: UNKNOWN
Classifier: Intended Audience :: Developers
Classifier: License :: OSI Approved :: MIT License
Classifier: Programming Language :: C++
Classifier: Programming Language :: Cython
Classifier: Programming Language :: Python :: 2.7
Classifier: Programming Language :: Python :: 3.3
Classifier: Programming Language :: Python :: 3.4
Classifier: Programming Language :: Python :: 3.5
Classifier: Programming Language :: Python :: 3.6
